[
    {
        "model": "client.Order",
        "pk": 1,
        "fields": {
            "total_price": 84.27,
            "customer_id": 1
        }
    },
    {
        "model": "client.Order",
        "pk": 2,
        "fields": {
            "total_price": 64.33,
            "customer_id": 2
        }
    },
    {
        "model": "client.Order",
        "pk": 3,
        "fields": {
            "total_price": 84.27,
            "customer_id": 3
        }
    },
    {
        "model": "client.Order",
        "pk": 4,
        "fields": {
            "total_price": 63.07,
            "customer_id": 4
        }
    },
    {
        "model": "client.Order",
        "pk": 5,
        "fields": {
            "total_price": 64.33,
            "customer_id": 5
        }
    },
    {
        "model": "client.Order",
        "pk": 6,
        "fields": {
            "total_price": 62.01,
            "customer_id": 6
        }
    },
    {
        "model": "client.Order",
        "pk": 7,
        "fields": {
            "total_price": 84.27,
            "customer_id": 7
        }
    },
    {
        "model": "client.Order",
        "pk": 8,
        "fields": {
            "total_price": 138.33,
            "customer_id": 8
        }
    },
    {
        "model": "client.Order",
        "pk": 9,
        "fields": {
            "total_price": 64.33,
            "customer_id": 9
        }
    },
    {
        "model": "client.Order",
        "pk": 10,
        "fields": {
            "total_price": 55.65,
            "customer_id": 10
        }
    },
    {
        "model": "client.Order",
        "pk": 11,
        "fields": {
            "total_price": 60.0,
            "customer_id": 11
        }
    },
    {
        "model": "client.Order",
        "pk": 12,
        "fields": {
            "total_price": 62.01,
            "customer_id": 12
        }
    },
    {
        "model": "client.Order",
        "pk": 13,
        "fields": {
            "total_price": 64.33,
            "customer_id": 13
        }
    },
    {
        "model": "client.Order",
        "pk": 14,
        "fields": {
            "total_price": 138.33,
            "customer_id": 14
        }
    },
    {
        "model": "client.Order",
        "pk": 15,
        "fields": {
            "total_price": 62.01,
            "customer_id": 15
        }
    },
    {
        "model": "client.Order",
        "pk": 16,
        "fields": {
            "total_price": 114.48,
            "customer_id": 16
        }
    },
    {
        "model": "client.Order",
        "pk": 17,
        "fields": {
            "total_price": 50.35,
            "customer_id": 17
        }
    },
    {
        "model": "client.Order",
        "pk": 18,
        "fields": {
            "total_price": 31.8,
            "customer_id": 18
        }
    },
    {
        "model": "client.Order",
        "pk": 19,
        "fields": {
            "total_price": 78.44,
            "customer_id": 19
        }
    },
    {
        "model": "client.Order",
        "pk": 20,
        "fields": {
            "total_price": 138.33,
            "customer_id": 20
        }
    },
    {
        "model": "client.Order",
        "pk": 21,
        "fields": {
            "total_price": 62.01,
            "customer_id": 21
        }
    },
    {
        "model": "client.Order",
        "pk": 22,
        "fields": {
            "total_price": 64.33,
            "customer_id": 22
        }
    },
    {
        "model": "client.Order",
        "pk": 23,
        "fields": {
            "total_price": 60.0,
            "customer_id": 23
        }
    },
    {
        "model": "client.Order",
        "pk": 24,
        "fields": {
            "total_price": 64.33,
            "customer_id": 24
        }
    },
    {
        "model": "client.Order",
        "pk": 25,
        "fields": {
            "total_price": 62.01,
            "customer_id": 25
        }
    },
    {
        "model": "client.Order",
        "pk": 26,
        "fields": {
            "total_price": 64.33,
            "customer_id": 26
        }
    },
    {
        "model": "client.Order",
        "pk": 27,
        "fields": {
            "total_price": 64.33,
            "customer_id": 27
        }
    },
    {
        "model": "client.Order",
        "pk": 28,
        "fields": {
            "total_price": 62.01,
            "customer_id": 28
        }
    },
    {
        "model": "client.Order",
        "pk": 29,
        "fields": {
            "total_price": 84.27,
            "customer_id": 29
        }
    },
    {
        "model": "client.Order",
        "pk": 30,
        "fields": {
            "total_price": 65.19,
            "customer_id": 30
        }
    },
    {
        "model": "client.Order",
        "pk": 31,
        "fields": {
            "total_price": 62.01,
            "customer_id": 31
        }
    },
    {
        "model": "client.Order",
        "pk": 32,
        "fields": {
            "total_price": 60.0,
            "customer_id": 32
        }
    },
    {
        "model": "client.Order",
        "pk": 33,
        "fields": {
            "total_price": 62.01,
            "customer_id": 33
        }
    },
    {
        "model": "client.Order",
        "pk": 34,
        "fields": {
            "total_price": 64.33,
            "customer_id": 34
        }
    },
    {
        "model": "client.Order",
        "pk": 35,
        "fields": {
            "total_price": 76.32,
            "customer_id": 35
        }
    },
    {
        "model": "client.Order",
        "pk": 36,
        "fields": {
            "total_price": 65.19,
            "customer_id": 36
        }
    },
    {
        "model": "client.Order",
        "pk": 37,
        "fields": {
            "total_price": 15.9,
            "customer_id": 37
        }
    },
    {
        "model": "client.Order",
        "pk": 38,
        "fields": {
            "total_price": 64.33,
            "customer_id": 38
        }
    },
    {
        "model": "client.Order",
        "pk": 39,
        "fields": {
            "total_price": 138.33,
            "customer_id": 39
        }
    },
    {
        "model": "client.Order",
        "pk": 40,
        "fields": {
            "total_price": 64.33,
            "customer_id": 40
        }
    },
    {
        "model": "client.Order",
        "pk": 41,
        "fields": {
            "total_price": 62.01,
            "customer_id": 41
        }
    },
    {
        "model": "client.Order",
        "pk": 42,
        "fields": {
            "total_price": 62.01,
            "customer_id": 42
        }
    },
    {
        "model": "client.Order",
        "pk": 43,
        "fields": {
            "total_price": 84.27,
            "customer_id": 43
        }
    },
    {
        "model": "client.Order",
        "pk": 44,
        "fields": {
            "total_price": 64.33,
            "customer_id": 44
        }
    },
    {
        "model": "client.Order",
        "pk": 45,
        "fields": {
            "total_price": 62.01,
            "customer_id": 45
        }
    },
    {
        "model": "client.Order",
        "pk": 46,
        "fields": {
            "total_price": 138.33,
            "customer_id": 46
        }
    },
    {
        "model": "client.Order",
        "pk": 47,
        "fields": {
            "total_price": 62.01,
            "customer_id": 47
        }
    },
    {
        "model": "client.Order",
        "pk": 48,
        "fields": {
            "total_price": 62.01,
            "customer_id": 48
        }
    },
    {
        "model": "client.Order",
        "pk": 49,
        "fields": {
            "total_price": 64.33,
            "customer_id": 49
        }
    },
    {
        "model": "client.Order",
        "pk": 50,
        "fields": {
            "total_price": 40.92,
            "customer_id": 50
        }
    },
    {
        "model": "client.Order",
        "pk": 51,
        "fields": {
            "total_price": 64.33,
            "customer_id": 1
        }
    },
    {
        "model": "client.Order",
        "pk": 52,
        "fields": {
            "total_price": 62.01,
            "customer_id": 2
        }
    },
    {
        "model": "client.Order",
        "pk": 53,
        "fields": {
            "total_price": 64.33,
            "customer_id": 3
        }
    },
    {
        "model": "client.Order",
        "pk": 54,
        "fields": {
            "total_price": 84.27,
            "customer_id": 4
        }
    },
    {
        "model": "client.Order",
        "pk": 55,
        "fields": {
            "total_price": 55.65,
            "customer_id": 5
        }
    },
    {
        "model": "client.Order",
        "pk": 56,
        "fields": {
            "total_price": 64.33,
            "customer_id": 6
        }
    },
    {
        "model": "client.Order",
        "pk": 57,
        "fields": {
            "total_price": 64.33,
            "customer_id": 7
        }
    },
    {
        "model": "client.Order",
        "pk": 58,
        "fields": {
            "total_price": 64.33,
            "customer_id": 8
        }
    },
    {
        "model": "client.Order",
        "pk": 59,
        "fields": {
            "total_price": 77.38,
            "customer_id": 9
        }
    },
    {
        "model": "client.Order",
        "pk": 60,
        "fields": {
            "total_price": 64.33,
            "customer_id": 10
        }
    },
    {
        "model": "client.Order",
        "pk": 61,
        "fields": {
            "total_price": 138.33,
            "customer_id": 11
        }
    },
    {
        "model": "client.Order",
        "pk": 62,
        "fields": {
            "total_price": 64.33,
            "customer_id": 12
        }
    },
    {
        "model": "client.Order",
        "pk": 63,
        "fields": {
            "total_price": 71.55,
            "customer_id": 13
        }
    },
    {
        "model": "client.Order",
        "pk": 64,
        "fields": {
            "total_price": 62.01,
            "customer_id": 14
        }
    },
    {
        "model": "client.Order",
        "pk": 65,
        "fields": {
            "total_price": 114.48,
            "customer_id": 15
        }
    },
    {
        "model": "client.Order",
        "pk": 66,
        "fields": {
            "total_price": 84.27,
            "customer_id": 16
        }
    },
    {
        "model": "client.Order",
        "pk": 67,
        "fields": {
            "total_price": 138.33,
            "customer_id": 17
        }
    },
    {
        "model": "client.Order",
        "pk": 68,
        "fields": {
            "total_price": 62.01,
            "customer_id": 18
        }
    },
    {
        "model": "client.Order",
        "pk": 69,
        "fields": {
            "total_price": 64.33,
            "customer_id": 19
        }
    },
    {
        "model": "client.Order",
        "pk": 70,
        "fields": {
            "total_price": 138.33,
            "customer_id": 20
        }
    },
    {
        "model": "client.Order",
        "pk": 71,
        "fields": {
            "total_price": 64.33,
            "customer_id": 21
        }
    },
    {
        "model": "client.Order",
        "pk": 72,
        "fields": {
            "total_price": 64.33,
            "customer_id": 22
        }
    },
    {
        "model": "client.Order",
        "pk": 73,
        "fields": {
            "total_price": 62.01,
            "customer_id": 23
        }
    },
    {
        "model": "client.Order",
        "pk": 74,
        "fields": {
            "total_price": 55.65,
            "customer_id": 24
        }
    },
    {
        "model": "client.Order",
        "pk": 75,
        "fields": {
            "total_price": 55.65,
            "customer_id": 25
        }
    },
    {
        "model": "client.Order",
        "pk": 76,
        "fields": {
            "total_price": 55.65,
            "customer_id": 26
        }
    },
    {
        "model": "client.Order",
        "pk": 77,
        "fields": {
            "total_price": 64.33,
            "customer_id": 27
        }
    },
    {
        "model": "client.Order",
        "pk": 78,
        "fields": {
            "total_price": 64.33,
            "customer_id": 28
        }
    },
    {
        "model": "client.Order",
        "pk": 79,
        "fields": {
            "total_price": 55.65,
            "customer_id": 29
        }
    },
    {
        "model": "client.Order",
        "pk": 80,
        "fields": {
            "total_price": 55.65,
            "customer_id": 30
        }
    },
    {
        "model": "client.Order",
        "pk": 81,
        "fields": {
            "total_price": 55.65,
            "customer_id": 31
        }
    },
    {
        "model": "client.Order",
        "pk": 82,
        "fields": {
            "total_price": 64.33,
            "customer_id": 32
        }
    },
    {
        "model": "client.Order",
        "pk": 83,
        "fields": {
            "total_price": 55.65,
            "customer_id": 33
        }
    },
    {
        "model": "client.Order",
        "pk": 84,
        "fields": {
            "total_price": 55.65,
            "customer_id": 34
        }
    },
    {
        "model": "client.Order",
        "pk": 85,
        "fields": {
            "total_price": 55.65,
            "customer_id": 35
        }
    },
    {
        "model": "client.Order",
        "pk": 86,
        "fields": {
            "total_price": 55.65,
            "customer_id": 36
        }
    },
    {
        "model": "client.Order",
        "pk": 87,
        "fields": {
            "total_price": 55.65,
            "customer_id": 37
        }
    },
    {
        "model": "client.Order",
        "pk": 88,
        "fields": {
            "total_price": 55.65,
            "customer_id": 38
        }
    },
    {
        "model": "client.Order",
        "pk": 89,
        "fields": {
            "total_price": 55.65,
            "customer_id": 39
        }
    },
    {
        "model": "client.Order",
        "pk": 90,
        "fields": {
            "total_price": 62.01,
            "customer_id": 40
        }
    },
    {
        "model": "client.Order",
        "pk": 91,
        "fields": {
            "total_price": 55.65,
            "customer_id": 41
        }
    },
    {
        "model": "client.Order",
        "pk": 92,
        "fields": {
            "total_price": 77.38,
            "customer_id": 42
        }
    },
    {
        "model": "client.Order",
        "pk": 93,
        "fields": {
            "total_price": 64.33,
            "customer_id": 43
        }
    },
    {
        "model": "client.Order",
        "pk": 94,
        "fields": {
            "total_price": 64.33,
            "customer_id": 44
        }
    },
    {
        "model": "client.Order",
        "pk": 95,
        "fields": {
            "total_price": 55.65,
            "customer_id": 45
        }
    },
    {
        "model": "client.Order",
        "pk": 96,
        "fields": {
            "total_price": 64.33,
            "customer_id": 46
        }
    },
    {
        "model": "client.Order",
        "pk": 97,
        "fields": {
            "total_price": 55.65,
            "customer_id": 47
        }
    },
    {
        "model": "client.Order",
        "pk": 98,
        "fields": {
            "total_price": 55.65,
            "customer_id": 48
        }
    },
    {
        "model": "client.Order",
        "pk": 99,
        "fields": {
            "total_price": 55.65,
            "customer_id": 49
        }
    },
    {
        "model": "client.Order",
        "pk": 100,
        "fields": {
            "total_price": 55.65,
            "customer_id": 50
        }
    },
    {
        "model": "client.Order",
        "pk": 101,
        "fields": {
            "total_price": 64.33,
            "customer_id": 1
        }
    },
    {
        "model": "client.Order",
        "pk": 102,
        "fields": {
            "total_price": 64.33,
            "customer_id": 2
        }
    },
    {
        "model": "client.Order",
        "pk": 103,
        "fields": {
            "total_price": 56.71,
            "customer_id": 3
        }
    },
    {
        "model": "client.Order",
        "pk": 104,
        "fields": {
            "total_price": 45.05,
            "customer_id": 4
        }
    },
    {
        "model": "client.Order",
        "pk": 105,
        "fields": {
            "total_price": 78.97,
            "customer_id": 5
        }
    },
    {
        "model": "client.Order",
        "pk": 106,
        "fields": {
            "total_price": 70.49,
            "customer_id": 6
        }
    },
    {
        "model": "client.Order",
        "pk": 107,
        "fields": {
            "total_price": 70.49,
            "customer_id": 7
        }
    },
    {
        "model": "client.Order",
        "pk": 108,
        "fields": {
            "total_price": 70.49,
            "customer_id": 8
        }
    },
    {
        "model": "client.Order",
        "pk": 109,
        "fields": {
            "total_price": 69.43,
            "customer_id": 9
        }
    },
    {
        "model": "client.Order",
        "pk": 110,
        "fields": {
            "total_price": 67.31,
            "customer_id": 10
        }
    },
    {
        "model": "client.Order",
        "pk": 111,
        "fields": {
            "total_price": 69.43,
            "customer_id": 11
        }
    },
    {
        "model": "client.Order",
        "pk": 112,
        "fields": {
            "total_price": 69.43,
            "customer_id": 12
        }
    },
    {
        "model": "client.Order",
        "pk": 113,
        "fields": {
            "total_price": 138.65,
            "customer_id": 13
        }
    },
    {
        "model": "client.Order",
        "pk": 114,
        "fields": {
            "total_price": 70.49,
            "customer_id": 14
        }
    },
    {
        "model": "client.Order",
        "pk": 115,
        "fields": {
            "total_price": 21.94,
            "customer_id": 15
        }
    },
    {
        "model": "client.Order",
        "pk": 116,
        "fields": {
            "total_price": 69.43,
            "customer_id": 16
        }
    },
    {
        "model": "client.Order",
        "pk": 117,
        "fields": {
            "total_price": 214.7,
            "customer_id": 17
        }
    },
    {
        "model": "client.Order",
        "pk": 118,
        "fields": {
            "total_price": 45.05,
            "customer_id": 18
        }
    },
    {
        "model": "client.Order",
        "pk": 119,
        "fields": {
            "total_price": 31.48,
            "customer_id": 19
        }
    },
    {
        "model": "client.Order",
        "pk": 120,
        "fields": {
            "total_price": 67.31,
            "customer_id": 20
        }
    },
    {
        "model": "client.Order",
        "pk": 121,
        "fields": {
            "total_price": 62.01,
            "customer_id": 21
        }
    },
    {
        "model": "client.Order",
        "pk": 122,
        "fields": {
            "total_price": 62.01,
            "customer_id": 22
        }
    },
    {
        "model": "client.Order",
        "pk": 123,
        "fields": {
            "total_price": 69.43,
            "customer_id": 23
        }
    },
    {
        "model": "client.Order",
        "pk": 124,
        "fields": {
            "total_price": 67.31,
            "customer_id": 24
        }
    },
    {
        "model": "client.Order",
        "pk": 125,
        "fields": {
            "total_price": 67.31,
            "customer_id": 25
        }
    },
    {
        "model": "client.Order",
        "pk": 126,
        "fields": {
            "total_price": 62.01,
            "customer_id": 26
        }
    },
    {
        "model": "client.Order",
        "pk": 127,
        "fields": {
            "total_price": 69.43,
            "customer_id": 27
        }
    },
    {
        "model": "client.Order",
        "pk": 128,
        "fields": {
            "total_price": 70.49,
            "customer_id": 28
        }
    },
    {
        "model": "client.Order",
        "pk": 129,
        "fields": {
            "total_price": 56.71,
            "customer_id": 29
        }
    },
    {
        "model": "client.Order",
        "pk": 130,
        "fields": {
            "total_price": 67.31,
            "customer_id": 30
        }
    },
    {
        "model": "client.Order",
        "pk": 131,
        "fields": {
            "total_price": 70.49,
            "customer_id": 31
        }
    },
    {
        "model": "client.Order",
        "pk": 132,
        "fields": {
            "total_price": 70.49,
            "customer_id": 32
        }
    },
    {
        "model": "client.Order",
        "pk": 133,
        "fields": {
            "total_price": 62.01,
            "customer_id": 33
        }
    },
    {
        "model": "client.Order",
        "pk": 134,
        "fields": {
            "total_price": 45.05,
            "customer_id": 34
        }
    },
    {
        "model": "client.Order",
        "pk": 135,
        "fields": {
            "total_price": 67.31,
            "customer_id": 35
        }
    },
    {
        "model": "client.Order",
        "pk": 136,
        "fields": {
            "total_price": 69.43,
            "customer_id": 36
        }
    },
    {
        "model": "client.Order",
        "pk": 137,
        "fields": {
            "total_price": 69.43,
            "customer_id": 37
        }
    },
    {
        "model": "client.Order",
        "pk": 138,
        "fields": {
            "total_price": 56.71,
            "customer_id": 38
        }
    },
    {
        "model": "client.Order",
        "pk": 139,
        "fields": {
            "total_price": 70.49,
            "customer_id": 39
        }
    },
    {
        "model": "client.Order",
        "pk": 140,
        "fields": {
            "total_price": 70.49,
            "customer_id": 40
        }
    },
    {
        "model": "client.Order",
        "pk": 141,
        "fields": {
            "total_price": 67.31,
            "customer_id": 41
        }
    },
    {
        "model": "client.Order",
        "pk": 142,
        "fields": {
            "total_price": 70.49,
            "customer_id": 42
        }
    },
    {
        "model": "client.Order",
        "pk": 143,
        "fields": {
            "total_price": 67.31,
            "customer_id": 43
        }
    },
    {
        "model": "client.Order",
        "pk": 144,
        "fields": {
            "total_price": 62.01,
            "customer_id": 44
        }
    },
    {
        "model": "client.Order",
        "pk": 145,
        "fields": {
            "total_price": 69.43,
            "customer_id": 45
        }
    },
    {
        "model": "client.Order",
        "pk": 146,
        "fields": {
            "total_price": 70.49,
            "customer_id": 46
        }
    },
    {
        "model": "client.Order",
        "pk": 147,
        "fields": {
            "total_price": 70.49,
            "customer_id": 47
        }
    },
    {
        "model": "client.Order",
        "pk": 148,
        "fields": {
            "total_price": 69.43,
            "customer_id": 48
        }
    },
    {
        "model": "client.Order",
        "pk": 149,
        "fields": {
            "total_price": 70.49,
            "customer_id": 49
        }
    },
    {
        "model": "client.Order",
        "pk": 150,
        "fields": {
            "total_price": 56.71,
            "customer_id": 50
        }
    },
    {
        "model": "client.Order",
        "pk": 151,
        "fields": {
            "total_price": 67.31,
            "customer_id": 1
        }
    }
]
